<annotation>
	<folder>tosort</folder>
	<filename>jodaille_frelon_2019-08-24-170201_8mm.jpg</filename>
	<path>/home/jeremy/Documents/HornetKiller/hornet-detector-trainer/images/tosort/jodaille_frelon_2019-08-24-170201_8mm.jpg</path>
	<source>
		<database>Unknown</database>
	</source>
	<size>
		<width>1280</width>
		<height>720</height>
		<depth>3</depth>
	</size>
	<segmented>0</segmented>
	<object>
		<name>hornet</name>
		<pose>Unspecified</pose>
		<truncated>0</truncated>
		<difficult>0</difficult>
		<bndbox>
			<xmin>446</xmin>
			<ymin>252</ymin>
			<xmax>522</xmax>
			<ymax>354</ymax>
		</bndbox>
	</object>
	<object>
		<name>bee</name>
		<pose>Unspecified</pose>
		<truncated>0</truncated>
		<difficult>0</difficult>
		<bndbox>
			<xmin>1009</xmin>
			<ymin>233</ymin>
			<xmax>1054</xmax>
			<ymax>288</ymax>
		</bndbox>
	</object>
	<object>
		<name>bee</name>
		<pose>Unspecified</pose>
		<truncated>0</truncated>
		<difficult>0</difficult>
		<bndbox>
			<xmin>1054</xmin>
			<ymin>343</ymin>
			<xmax>1097</xmax>
			<ymax>419</ymax>
		</bndbox>
	</object>
	<object>
		<name>bee</name>
		<pose>Unspecified</pose>
		<truncated>0</truncated>
		<difficult>0</difficult>
		<bndbox>
			<xmin>1083</xmin>
			<ymin>433</ymin>
			<xmax>1148</xmax>
			<ymax>515</ymax>
		</bndbox>
	</object>
	<object>
		<name>bee</name>
		<pose>Unspecified</pose>
		<truncated>0</truncated>
		<difficult>0</difficult>
		<bndbox>
			<xmin>812</xmin>
			<ymin>564</ymin>
			<xmax>878</xmax>
			<ymax>614</ymax>
		</bndbox>
	</object>
</annotation>
