<annotation>
	<folder>train</folder>
	<filename>Entree_de_ruche_protegee_contre_les_frelons_par_une_grille.jpg</filename>
	<path>/home/jeremy/Documents/HornetKiller/images/train/Entree_de_ruche_protegee_contre_les_frelons_par_une_grille.jpg</path>
	<source>
		<database>Unknown</database>
	</source>
	<size>
		<width>960</width>
		<height>720</height>
		<depth>3</depth>
	</size>
	<segmented>0</segmented>
	<object>
		<name>bee</name>
		<pose>Unspecified</pose>
		<truncated>0</truncated>
		<difficult>0</difficult>
		<bndbox>
			<xmin>317</xmin>
			<ymin>184</ymin>
			<xmax>334</xmax>
			<ymax>205</ymax>
		</bndbox>
	</object>
	<object>
		<name>bee</name>
		<pose>Unspecified</pose>
		<truncated>0</truncated>
		<difficult>0</difficult>
		<bndbox>
			<xmin>177</xmin>
			<ymin>393</ymin>
			<xmax>191</xmax>
			<ymax>418</ymax>
		</bndbox>
	</object>
	<object>
		<name>bee</name>
		<pose>Unspecified</pose>
		<truncated>0</truncated>
		<difficult>0</difficult>
		<bndbox>
			<xmin>168</xmin>
			<ymin>336</ymin>
			<xmax>188</xmax>
			<ymax>353</ymax>
		</bndbox>
	</object>
	<object>
		<name>bee</name>
		<pose>Unspecified</pose>
		<truncated>0</truncated>
		<difficult>0</difficult>
		<bndbox>
			<xmin>160</xmin>
			<ymin>379</ymin>
			<xmax>177</xmax>
			<ymax>407</ymax>
		</bndbox>
	</object>
</annotation>
