<annotation>
	<folder>tosort</folder>
	<filename>jodaille_frelon_2019-09-19-143711_Left.jpg</filename>
	<path>/home/jeremy/Documents/HornetKiller/hornet-detector-trainer/images/tosort/jodaille_frelon_2019-09-19-143711_Left.jpg</path>
	<source>
		<database>Unknown</database>
	</source>
	<size>
		<width>1280</width>
		<height>720</height>
		<depth>3</depth>
	</size>
	<segmented>0</segmented>
	<object>
		<name>hornet</name>
		<pose>Unspecified</pose>
		<truncated>0</truncated>
		<difficult>0</difficult>
		<bndbox>
			<xmin>684</xmin>
			<ymin>302</ymin>
			<xmax>737</xmax>
			<ymax>379</ymax>
		</bndbox>
	</object>
	<object>
		<name>bee</name>
		<pose>Unspecified</pose>
		<truncated>0</truncated>
		<difficult>0</difficult>
		<bndbox>
			<xmin>1155</xmin>
			<ymin>511</ymin>
			<xmax>1187</xmax>
			<ymax>540</ymax>
		</bndbox>
	</object>
</annotation>
